watchmen_dqc/__init__.py
watchmen_dqc/boot/__init__.py
watchmen_dqc/boot/boot.py
watchmen_dqc/common/__init__.py
watchmen_dqc/common/exception.py
watchmen_dqc/common/settings.py
watchmen_dqc/monitor/__init__.py
watchmen_dqc/monitor/monitor_data_service.py
watchmen_dqc/monitor/rule/__init__.py
watchmen_dqc/monitor/rule/data_service_utils.py
watchmen_dqc/monitor/rule/date_range.py
watchmen_dqc/monitor/rule/disabled_rules.py
watchmen_dqc/monitor/rule/enum_service.py
watchmen_dqc/monitor/rule/factor_aggregate_value_not_in_range.py
watchmen_dqc/monitor/rule/factor_and_another.py
watchmen_dqc/monitor/rule/factor_avg_not_in_range.py
watchmen_dqc/monitor/rule/factor_common_value_not_in_range.py
watchmen_dqc/monitor/rule/factor_common_value_over_coverage.py
watchmen_dqc/monitor/rule/factor_empty_over_coverage.py
watchmen_dqc/monitor/rule/factor_is_blank.py
watchmen_dqc/monitor/rule/factor_is_empty.py
watchmen_dqc/monitor/rule/factor_match_regexp.py
watchmen_dqc/monitor/rule/factor_max_not_in_range.py
watchmen_dqc/monitor/rule/factor_median_not_in_range.py
watchmen_dqc/monitor/rule/factor_min_not_in_range.py
watchmen_dqc/monitor/rule/factor_mismatch_enum.py
watchmen_dqc/monitor/rule/factor_mismatch_regexp.py
watchmen_dqc/monitor/rule/factor_mismatch_type.py
watchmen_dqc/monitor/rule/factor_not_in_range.py
watchmen_dqc/monitor/rule/factor_quantile_not_in_range.py
watchmen_dqc/monitor/rule/factor_stdev_not_in_range.py
watchmen_dqc/monitor/rule/factor_string_length_mismatch.py
watchmen_dqc/monitor/rule/factor_string_length_not_in_range.py
watchmen_dqc/monitor/rule/factor_use_regexp.py
watchmen_dqc/monitor/rule/factor_value_assert.py
watchmen_dqc/monitor/rule/retrieve_all_data_rules.py
watchmen_dqc/monitor/rule/retrieve_data_rules_utils.py
watchmen_dqc/monitor/rule/retrieve_distinct_data_rules.py
watchmen_dqc/monitor/rule/rows_count_mismatch_with_another.py
watchmen_dqc/monitor/rule/rows_no_change.py
watchmen_dqc/monitor/rule/rows_not_exists.py
watchmen_dqc-18.0.1.dist-info/METADATA
watchmen_dqc-18.0.1.dist-info/WHEEL
watchmen_dqc-18.0.1.dist-info/licenses/LICENSE
watchmen_dqc-18.0.1.dist-info/RECORD
